setup.py
Panipuri.egg-info/PKG-INFO
Panipuri.egg-info/SOURCES.txt
Panipuri.egg-info/dependency_links.txt
Panipuri.egg-info/top_level.txt
panipuri/__init__.py
panipuri/backends/CacheBackend.py
panipuri/backends/DBMCache.py
panipuri/backends/FilesystemDataframeCache.py
panipuri/backends/SQLiteCache.py
panipuri/backends/__init__.py
test/TestBackend.py
test/TestWrapper.py
test/__init__.py