Metadata-Version: 1.0
Name: Panipuri
Version: 0.01.1
Summary: Locally cache scraped data.
Home-page: https://github.com/stucchio/panipuri
Author: Chris Stucchio
Author-email: stucchio@gmail.com
License: UNKNOWN
Platform: UNKNOWN
